zarr/__init__.py
zarr/_compat.py
zarr/_version.py
zarr/convenience.py
zarr/creation.py
zarr/dtype.py
zarr/errors.py
zarr/py.typed
zarr/registry.py
zarr/abc/__init__.py
zarr/abc/buffer.py
zarr/abc/codec.py
zarr/abc/metadata.py
zarr/abc/store.py
zarr/api/__init__.py
zarr/api/asynchronous.py
zarr/api/synchronous.py
zarr/buffer/__init__.py
zarr/buffer/cpu.py
zarr/buffer/gpu.py
zarr/codecs/__init__.py
zarr/codecs/_v2.py
zarr/codecs/blosc.py
zarr/codecs/bytes.py
zarr/codecs/crc32c_.py
zarr/codecs/gzip.py
zarr/codecs/sharding.py
zarr/codecs/transpose.py
zarr/codecs/vlen_utf8.py
zarr/codecs/zstd.py
zarr/core/__init__.py
zarr/core/_info.py
zarr/core/_tree.py
zarr/core/array.py
zarr/core/array_spec.py
zarr/core/attributes.py
zarr/core/chunk_grids.py
zarr/core/chunk_key_encodings.py
zarr/core/codec_pipeline.py
zarr/core/common.py
zarr/core/config.py
zarr/core/group.py
zarr/core/indexing.py
zarr/core/sync.py
zarr/core/sync_group.py
zarr/core/buffer/__init__.py
zarr/core/buffer/core.py
zarr/core/buffer/cpu.py
zarr/core/buffer/gpu.py
zarr/core/dtype/__init__.py
zarr/core/dtype/common.py
zarr/core/dtype/registry.py
zarr/core/dtype/wrapper.py
zarr/core/dtype/npy/__init__.py
zarr/core/dtype/npy/bool.py
zarr/core/dtype/npy/bytes.py
zarr/core/dtype/npy/common.py
zarr/core/dtype/npy/complex.py
zarr/core/dtype/npy/float.py
zarr/core/dtype/npy/int.py
zarr/core/dtype/npy/string.py
zarr/core/dtype/npy/structured.py
zarr/core/dtype/npy/time.py
zarr/core/metadata/__init__.py
zarr/core/metadata/common.py
zarr/core/metadata/v2.py
zarr/core/metadata/v3.py
zarr/storage/__init__.py
zarr/storage/_common.py
zarr/storage/_fsspec.py
zarr/storage/_local.py
zarr/storage/_logging.py
zarr/storage/_memory.py
zarr/storage/_obstore.py
zarr/storage/_utils.py
zarr/storage/_wrapper.py
zarr/storage/_zip.py
zarr/testing/__init__.py
zarr/testing/buffer.py
zarr/testing/stateful.py
zarr/testing/store.py
zarr/testing/strategies.py
zarr/testing/utils.py
zarr-3.1.0.dist-info/METADATA
zarr-3.1.0.dist-info/WHEEL
zarr-3.1.0.dist-info/licenses/LICENSE.txt
zarr-3.1.0.dist-info/RECORD
