Metadata-Version: 2.4
Name: zarr
Version: 3.1.0
Summary: An implementation of chunked, compressed, N-dimensional arrays for Python
Project-URL: Bug Tracker, https://github.com/zarr-developers/zarr-python/issues
Project-URL: Changelog, https://zarr.readthedocs.io/en/stable/release-notes.html
Project-URL: Discussions, https://github.com/zarr-developers/zarr-python/discussions
Project-URL: Documentation, https://zarr.readthedocs.io/
Project-URL: Homepage, https://github.com/zarr-developers/zarr-python
Author-email: Alistair Miles <alimanfoo@googlemail.com>
Maintainer: jakirkham, Norman Rzepka, Ryan Abernathey, David Stansby, Deepak Cherian
Maintainer-email: Davis Bennett <davis.v.bennett@gmail.com>, Josh Moore <josh@openmicroscopy.org>, Joe Hamman <joe@earthmover.io>, Juan Nunez-Iglesias <juan.nunez-iglesias@monash.edu>, Martin Durant <mdurant@anaconda.com>, Tom Augspurger <tom.w.augspurger@gmail.com>
License: MIT License
License-File: LICENSE.txt
Keywords: Python,compressed,ndimensional-arrays,zarr
Classifier: Development Status :: 6 - Mature
Classifier: Intended Audience :: Developers
Classifier: Intended Audience :: Information Technology
Classifier: Intended Audience :: Science/Research
Classifier: License :: OSI Approved :: MIT License
Classifier: Operating System :: Unix
Classifier: Programming Language :: Python
Classifier: Programming Language :: Python :: 3
Classifier: Programming Language :: Python :: 3.11
Classifier: Programming Language :: Python :: 3.12
Classifier: Programming Language :: Python :: 3.13
Classifier: Topic :: Software Development :: Libraries :: Python Modules
Requires-Python: >=3.11
Requires-Dist: donfig>=0.8
Requires-Dist: numcodecs[crc32c]>=0.14
Requires-Dist: numpy>=1.26
Requires-Dist: packaging>=22.0
Requires-Dist: typing-extensions>=4.9
Provides-Extra: docs
Requires-Dist: astroid<4; extra == 'docs'
Requires-Dist: numcodecs[msgpack]; extra == 'docs'
Requires-Dist: numpydoc; extra == 'docs'
Requires-Dist: pydata-sphinx-theme; extra == 'docs'
Requires-Dist: pytest; extra == 'docs'
Requires-Dist: rich; extra == 'docs'
Requires-Dist: s3fs>=2023.10.0; extra == 'docs'
Requires-Dist: sphinx-autoapi==3.4.0; extra == 'docs'
Requires-Dist: sphinx-autobuild>=2021.3.14; extra == 'docs'
Requires-Dist: sphinx-copybutton; extra == 'docs'
Requires-Dist: sphinx-design; extra == 'docs'
Requires-Dist: sphinx-issues; extra == 'docs'
Requires-Dist: sphinx-reredirects; extra == 'docs'
Requires-Dist: sphinx==8.1.3; extra == 'docs'
Requires-Dist: towncrier; extra == 'docs'
Provides-Extra: gpu
Requires-Dist: cupy-cuda12x; extra == 'gpu'
Provides-Extra: optional
Requires-Dist: rich; extra == 'optional'
Requires-Dist: universal-pathlib; extra == 'optional'
Provides-Extra: remote
Requires-Dist: fsspec>=2023.10.0; extra == 'remote'
Requires-Dist: obstore>=0.5.1; extra == 'remote'
Provides-Extra: remote-tests
Requires-Dist: botocore; extra == 'remote-tests'
Requires-Dist: fsspec>=2023.10.0; extra == 'remote-tests'
Requires-Dist: moto[s3,server]; extra == 'remote-tests'
Requires-Dist: obstore>=0.5.1; extra == 'remote-tests'
Requires-Dist: requests; extra == 'remote-tests'
Requires-Dist: s3fs>=2023.10.0; extra == 'remote-tests'
Provides-Extra: test
Requires-Dist: coverage; extra == 'test'
Requires-Dist: hypothesis; extra == 'test'
Requires-Dist: mypy; extra == 'test'
Requires-Dist: packaging; extra == 'test'
Requires-Dist: pytest-accept; extra == 'test'
Requires-Dist: pytest-asyncio; extra == 'test'
Requires-Dist: pytest-cov; extra == 'test'
Requires-Dist: pytest-xdist; extra == 'test'
Requires-Dist: pytest<8.4; extra == 'test'
Requires-Dist: rich; extra == 'test'
Requires-Dist: tomlkit; extra == 'test'
Requires-Dist: uv; extra == 'test'
